APX Booth Multiplier/Multiplier.v
module MUL 
(
      input  reset,
      input  clk,
      input  [31:0] read_a, read_x,
      output reg [31:0] result
);

wire [15:0] read_a_p;
wire [15:0] read_x_p;
assign read_a_p = read_a [15:0];
assign read_x_p = read_x [15:0];

reg   [2:0]  c = 0;
reg   [31:0] partial_product = 0;
reg   [31:0] shifted_pp = 0;
reg   [15:0] i = 0, j = 0;
reg   flag = 0, temp = 0;
wire  [15:0] tows_comp;

assign tows_comp = (~read_a_p) + 1'b1;

always @(posedge clk) 
begin
      if (reset == 1) 
      begin
            c = 0;
            partial_product = 0;
            shifted_pp = 0;
            i = 0; j = 0;
            flag = 0; temp = 0;
            result = 0;
      end
      if (reset == 0) 
      begin
      
         if (!flag)
            c = {read_x_p [1], read_x_p [0], 1'b0};
            flag = 1;
            case (c)
            3'b000,3'b111: begin
                  if(i < 8)
                  begin  i = i + 1;
                  c = {read_x_p [2*i+1], read_x_p [2*i], read_x_p [2*i-1]}; 
                  end else
                  c = 3'bxxx;
            end
            3'b001,3'b010: begin
                  if(i < 8)
                  begin i = i + 1;
                  c = {read_a_p [2*i+1], read_x_p [2*i], read_x_p[2*i-1]};
                  partial_product = {{16{read_a_p[15]}}, read_a_p};
                  if(i == 1'b1)
                        result = partial_product;
                  else begin
                        temp = partial_product[31];
                        j = i - 1;
                        j = j << 1;
                        shifted_pp = partial_product << j;
                        shifted_pp = {temp, shifted_pp[30:0]};
                        result = result + shifted_pp;
                  end
                  end else 
                  c = 3'bxxx;
            end
            3'b011: begin
                  if(i < 8)
                  begin i = i + 1;
                  c = {read_x_p [2*i+1], read_x_p [2*i], read_x_p [2*i-1]};
                  partial_product = {{15{read_a_p[15]}}, read_a_p,1'b0};
                  if(i == 1'b1)
                        result = partial_product;
                  else begin
                        temp = partial_product [31];
                        j = i - 1;
                        j = j << 1;
                        shifted_pp = partial_product << j;
                        shifted_pp = {temp, shifted_pp[30:0]};
                        result = result + shifted_pp;
                  end
                  end else 
                  c = 3'bxxx;
            end
            3'b100: begin
                  if(i < 8)
                  begin
                  i = i + 1;
                  c = {read_x_p [2*i+1], read_x_p [2*i], read_x_p [2*i-1]};
                  partial_product = {{15{tows_comp[15]}}, tows_comp, 1'b0};
                  if(i == 1'b1)
                        result = partial_product;
                  else begin
                        temp = partial_product[31];
                        j = i - 1;
                        j = j << 1;
                        shifted_pp = partial_product << j;
                        shifted_pp = {temp,shifted_pp[30:0]};
                        result = result + shifted_pp;
                  end
                  end else 
                  c = 3'bxxx;
            end
            3'b101, 3'b110: begin
                  if(i < 8)
                  begin
                  i = i + 1;
                  c = {read_x_p [2*i+1], read_x_p [2*i], read_x_p [2*i-1]};
                  partial_product = {{16{tows_comp[15]}}, tows_comp};
                  if(i == 1'b1)
                        result = partial_product;
                  else begin
                        temp = partial_product[31];
                        j = i - 1;
                        j = j << 1;
                        shifted_pp = partial_product << j;
                        shifted_pp = {temp, shifted_pp[30:0]};
                        result = result + shifted_pp;
                  end
                  end else 
                  c = 3'bxxx;
            end

            default:
            result = partial_product;
            endcase   

      end
end

endmodule

APX Booth Multiplier/Multiplier_tb.v
`include "Multiplier.v"
`timescale 1ns/1ps

module Multiplier_tb;

  reg clk;
  reg reset;
  reg [31:0] read_a;
  reg [31:0] read_x;
  wire [31:0] result;

  MUL mul(.clk(clk), .reset(reset), .read_a(read_a), .read_x(read_x), .result(result));

  always #1 clk = ~clk;

  initial begin
    $dumpfile("Approx_Multiplier.vcd");
    $dumpvars(0,Multiplier_tb);
    clk = 0;
    reset = 0;
    read_a = 16'b0000000000000011; read_x = 16'b0000000000000010;
    #50;
    reset = 1;
    #5;
    reset = 0;
    read_a = 16'b0000000000000010; read_x = 16'b0000000000001111;
    #50;
    reset = 1;
    #5;
    reset = 0;
    read_a = 16'b0000000100000110; read_x = 16'b0000000001001000;
    #50;
    reset = 1;
    #5;
    reset = 0;
    read_a = 16'b0000000000000111; read_x = 16'b0000001000001010;
    #50;
    reset = 1;
    #5;
    reset = 0;
    read_a = 16'b0000110000000001; read_x = 16'b0000010011011111;
    #50
    reset = 1;
    #5
    reset = 0;
    read_a = 16'b0000110101011001; read_x = 16'b0000011011011111;
    #50
    reset = 1;
    #5
    reset = 0;
    read_a = 16'b0010110101011001; read_x = 16'b0010011011011111;
    #50
    reset = 1;
    #5
    reset = 0;
    read_a = 16'b0010110000000001; read_x = 16'b1100110011011111;
    #50;
    reset = 1;
    #5;
    $finish;
  end

endmodule

APX Booth Multiplier/Approx_Multiplier.vcd
$date
	Fri May 19 19:59:27 2023
$end
$version
	Icarus Verilog
$end
$timescale
	1ps
$end
$scope module Multiplier_tb $end
$var wire 32 ! result [31:0] $end
$var reg 1 " clk $end
$var reg 32 # read_a [31:0] $end
$var reg 32 $ read_x [31:0] $end
$var reg 1 % reset $end
$scope module mul $end
$var wire 1 " clk $end
$var wire 32 & read_a [31:0] $end
$var wire 32 ' read_x [31:0] $end
$var wire 1 % reset $end
$var wire 16 ( tows_comp [15:0] $end
$var wire 16 ) read_x_p [15:0] $end
$var wire 16 * read_a_p [15:0] $end
$var reg 3 + c [2:0] $end
$var reg 1 , flag $end
$var reg 16 - i [15:0] $end
$var reg 16 . j [15:0] $end
$var reg 32 / partial_product [31:0] $end
$var reg 32 0 result [31:0] $end
$var reg 32 1 shifted_pp [31:0] $end
$var reg 1 2 temp $end
$upscope $end
$upscope $end
$enddefinitions $end
$comment Show the parameter values. $end
$dumpall
$end
#0
$dumpvars
02
b0 1
bx 0
b0 /
b0 .
b0 -
0,
b0 +
b11 *
b10 )
b1111111111111101 (
b10 '
b11 &
0%
b10 $
b11 #
0"
bx !
$end
#1000
b11111111111111111111111111111010 !
b11111111111111111111111111111010 0
b11111111111111111111111111111010 /
b1 -
1,
b1 +
1"
#2000
0"
#3000
b110 !
b110 0
b1100 1
b10 .
b11 /
b0 +
b10 -
1"
#4000
0"
#5000
b11 -
1"
#6000
0"
#7000
b100 -
1"
#8000
0"
#9000
b101 -
1"
#10000
0"
#11000
b110 -
1"
#12000
0"
#13000
b111 -
1"
#14000
0"
#15000
bx0 +
b1000 -
1"
#16000
0"
#17000
b11 !
b11 0
1"
#18000
0"
#19000
1"
#20000
0"
#21000
1"
#22000
0"
#23000
1"
#24000
0"
#25000
1"
#26000
0"
#27000
1"
#28000
0"
#29000
1"
#30000
0"
#31000
1"
#32000
0"
#33000
1"
#34000
0"
#35000
1"
#36000
0"
#37000
1"
#38000
0"
#39000
1"
#40000
0"
#41000
1"
#42000
0"
#43000
1"
#44000
0"
#45000
1"
#46000
0"
#47000
1"
#48000
0"
#49000
1"
#50000
0"
1%
#51000
b0 !
b0 0
0,
b0 .
b0 -
b0 1
b0 /
b0 +
1"
#52000
0"
#53000
1"
#54000
0"
#55000
b1111111111111110 (
b11111111111111111111111111111101 !
b11111111111111111111111111111101 0
b11111111111111111111111111111101 /
b1 -
1,
b111 +
b1111 )
b10 *
1"
b1111 $
b1111 '
b10 #
b10 &
0%
#56000
0"
#57000
b1 +
b10 -
1"
#58000
0"
#59000
b11101 !
b11101 0
b100000 1
b100 .
b10 /
b0 +
b11 -
1"
#60000
0"
#61000
b100 -
1"
#62000
0"
#63000
b101 -
1"
#64000
0"
#65000
b110 -
1"
#66000
0"
#67000
b111 -
1"
#68000
0"
#69000
bx0 +
b1000 -
1"
#70000
0"
#71000
b10 !
b10 0
1"
#72000
0"
#73000
1"
#74000
0"
#75000
1"
#76000
0"
#77000
1"
#78000
0"
#79000
1"
#80000
0"
#81000
1"
#82000
0"
#83000
1"
#84000
0"
#85000
1"
#86000
0"
#87000
1"
#88000
0"
#89000
1"
#90000
0"
#91000
1"
#92000
0"
#93000
1"
#94000
0"
#95000
1"
#96000
0"
#97000
1"
#98000
0"
#99000
1"
#100000
0"
#101000
1"
#102000
0"
#103000
1"
#104000
0"
#105000
b0 !
b0 0
0,
b0 .
b0 -
b0 1
b0 /
b0 +
1"
1%
#106000
0"
#107000
1"
#108000
0"
#109000
1"
#110000
b1111111011111010 (
b1001000 )
b100000110 *
0"
b1001000 $
b1001000 '
b100000110 #
b100000110 &
0%
#111000
b100 +
b1 -
1,
1"
#112000
0"
#113000
b11111111111111111111011111010000 !
b11111111111111111111011111010000 0
b11111111111111111111011111010000 1
b10 .
12
b11111111111111111111110111110100 /
b1 +
b10 -
1"
#114000
0"
#115000
b100000110000 !
b100000110000 0
b1000001100000 1
b100 .
02
b100000110 /
b10 +
b11 -
1"
#116000
0"
#117000
b100100110110000 !
b100100110110000 0
b100000110000000 1
b110 .
b0 +
b100 -
1"
#118000
0"
#119000
b101 -
1"
#120000
0"
#121000
b110 -
1"
#122000
0"
#123000
b111 -
1"
#124000
0"
#125000
bx0 +
b1000 -
1"
#126000
0"
#127000
b100000110 !
b100000110 0
1"
#128000
0"
#129000
1"
#130000
0"
#131000
1"
#132000
0"
#133000
1"
#134000
0"
#135000
1"
#136000
0"
#137000
1"
#138000
0"
#139000
1"
#140000
0"
#141000
1"
#142000
0"
#143000
1"
#144000
0"
#145000
1"
#146000
0"
#147000
1"
#148000
0"
#149000
1"
#150000
0"
#151000
1"
#152000
0"
#153000
1"
#154000
0"
#155000
1"
#156000
0"
#157000
1"
#158000
0"
#159000
1"
#160000
0"
1%
#161000
b0 !
b0 0
0,
b0 .
b0 -
b0 1
b0 /
b0 +
1"
#162000
0"
#163000
1"
#164000
0"
#165000
b1111111111111001 (
b11111111111111111111110111110100 !
b11111111111111111111110111110100 0
b11111111111111111111110111110100 /
b1 -
1,
b101 +
b1000001010 )
b111 *
1"
b1000001010 $
b1000001010 '
b111 #
b111 &
0%
#166000
0"
#167000
b11111111111111111111110111011000 !
b11111111111111111111110111011000 0
b11111111111111111111111111100100 1
b10 .
12
b11111111111111111111111111111001 /
b1 +
b10 -
1"
#168000
0"
#169000
b11111111111111111111111001001000 !
b11111111111111111111111001001000 0
b1110000 1
b100 .
02
b111 /
b0 +
b11 -
1"
#170000
0"
#171000
b100 +
b100 -
1"
#172000
0"
#173000
b11111111111111111111000001001000 !
b11111111111111111111000001001000 0
b11111111111111111111001000000000 1
b1000 .
12
b11111111111111111111111111110010 /
b1 +
b101 -
1"
#174000
0"
#175000
b110001001000 !
b110001001000 0
b1110000000000 1
b1010 .
02
b111 /
b0 +
b110 -
1"
#176000
0"
#177000
b111 -
1"
#178000
0"
#179000
bx0 +
b1000 -
1"
#180000
0"
#181000
b111 !
b111 0
1"
#182000
0"
#183000
1"
#184000
0"
#185000
1"
#186000
0"
#187000
1"
#188000
0"
#189000
1"
#190000
0"
#191000
1"
#192000
0"
#193000
1"
#194000
0"
#195000
1"
#196000
0"
#197000
1"
#198000
0"
#199000
1"
#200000
0"
#201000
1"
#202000
0"
#203000
1"
#204000
0"
#205000
1"
#206000
0"
#207000
1"
#208000
0"
#209000
1"
#210000
0"
#211000
1"
#212000
0"
#213000
1"
#214000
0"
#215000
b0 !
b0 0
0,
b0 .
b0 -
b0 1
b0 /
b0 +
1"
1%
#216000
0"
#217000
1"
#218000
0"
#219000
1"
#220000
b1111001111111111 (
b10011011111 )
b110000000001 *
0"
b10011011111 $
b10011011111 '
b110000000001 #
b110000000001 &
0%
#221000
b11111111111111111111001111111111 !
b11111111111111111111001111111111 0
b11111111111111111111001111111111 /
b1 -
1,
b111 +
1"
#222000
0"
#223000
b11 +
b10 -
1"
#224000
0"
#225000
b10111010000011111 !
b10111010000011111 0
b11000000000100000 1
b100 .
b1100000000010 /
b110 +
b11 -
1"
#226000
0"
#227000
b11111111111111100111001111011111 !
b11111111111111100111001111011111 0
b11111111111111001111111111000000 1
b110 .
12
b11111111111111111111001111111111 /
b1 +
b100 -
1"
#228000
0"
#229000
b10100111010011011111 !
b10100111010011011111 0
b11000000000100000000 1
b1000 .
02
b110000000001 /
b110 +
b101 -
1"
#230000
0"
#231000
b11111111110110100111000011011111 !
b11111111110110100111000011011111 0
b11111111110011111111110000000000 1
b1010 .
12
b11111111111111111111001111111111 /
b0 +
b110 -
1"
#232000
0"
#233000
b111 -
1"
#234000
0"
#235000
bx0 +
b1000 -
1"
#236000
0"
#237000
b11111111111111111111001111111111 !
b11111111111111111111001111111111 0
1"
#238000
0"
#239000
1"
#240000
0"
#241000
1"
#242000
0"
#243000
1"
#244000
0"
#245000
1"
#246000
0"
#247000
1"
#248000
0"
#249000
1"
#250000
0"
#251000
1"
#252000
0"
#253000
1"
#254000
0"
#255000
1"
#256000
0"
#257000
1"
#258000
0"
#259000
1"
#260000
0"
#261000
1"
#262000
0"
#263000
1"
#264000
0"
#265000
1"
#266000
0"
#267000
1"
#268000
0"
#269000
1"
#270000
0"
1%
#271000
b0 !
b0 0
02
0,
b0 .
b0 -
b0 1
b0 /
b0 +
1"
#272000
0"
#273000
1"
#274000
0"
#275000
b1111001010100111 (
b11111111111111111111001111111111 !
b11111111111111111111001111111111 0
b11111111111111111111001111111111 /
b1 -
1,
b111 +
b11011011111 )
b110101011001 *
1"
b11011011111 $
b11011011111 '
b110101011001 #
b110101011001 &
0%
#276000
0"
#277000
b11 +
b10 -
1"
#278000
0"
#279000
b11001111100011111 !
b11001111100011111 0
b11010101100100000 1
b100 .
b1101010110010 /
b110 +
b11 -
1"
#280000
0"
#281000
b11111111111111100100100011011111 !
b11111111111111100100100011011111 0
b11111111111111001010100111000000 1
b110 .
12
b11111111111111111111001010100111 /
b101 +
b100 -
1"
#282000
0"
#283000
b11111111111100001110111111011111 !
b11111111111100001110111111011111 0
b11111111111100101010011100000000 1
b1000 .
b11 +
b101 -
1"
#284000
0"
#285000
b10110111011011111011111 !
b10110111011011111011111 0
b11010101100100000000000 1
b1010 .
02
b1101010110010 /
b0 +
b110 -
1"
#286000
0"
#287000
b111 -
1"
#288000
0"
#289000
bx0 +
b1000 -
1"
#290000
0"
#291000
b1101010110010 !
b1101010110010 0
1"
#292000
0"
#293000
1"
#294000
0"
#295000
1"
#296000
0"
#297000
1"
#298000
0"
#299000
1"
#300000
0"
#301000
1"
#302000
0"
#303000
1"
#304000
0"
#305000
1"
#306000
0"
#307000
1"
#308000
0"
#309000
1"
#310000
0"
#311000
1"
#312000
0"
#313000
1"
#314000
0"
#315000
1"
#316000
0"
#317000
1"
#318000
0"
#319000
1"
#320000
0"
#321000
1"
#322000
0"
#323000
1"
#324000
0"
#325000
b0 !
b0 0
0,
b0 .
b0 -
b0 1
b0 /
b0 +
1"
1%
#326000
0"
#327000
1"
#328000
0"
#329000
1"
#330000
b1101001010100111 (
b10011011011111 )
b10110101011001 *
0"
b10011011011111 $
b10011011011111 '
b10110101011001 #
b10110101011001 &
0%
#331000
b11111111111111111101001010100111 !
b11111111111111111101001010100111 0
b11111111111111111101001010100111 /
b1 -
1,
b111 +
1"
#332000
0"
#333000
b11 +
b10 -
1"
#334000
0"
#335000
b1010111110111000111 !
b1010111110111000111 0
b1011010101100100000 1
b100 .
b101101010110010 /
b110 +
b11 -
1"
#336000
0"
#337000
b11111111111110100010011110000111 !
b11111111111110100010011110000111 0
b11111111111101001010100111000000 1
b110 .
12
b11111111111111111101001010100111 /
b101 +
b100 -
1"
#338000
0"
#339000
b11111111110011001100111010000111 !
b11111111110011001100111010000111 0
b11111111110100101010011100000000 1
b1000 .
b11 +
b101 -
1"
#340000
0"
#341000
b1001101111001011010000111 !
b1001101111001011010000111 0
b1011010101100100000000000 1
b1010 .
02
b101101010110010 /
b100 +
b110 -
1"
#342000
0"
#343000
b11111011100011000111011010000111 !
b11111011100011000111011010000111 0
b11111010010101001110000000000000 1
b1100 .
12
b11111111111111111010010101001110 /
b1 +
b111 -
1"
#344000
0"
#345000
b110111000101011011010000111 !
b110111000101011011010000111 0
b1011010101100100000000000000 1
b1110 .
02
b10110101011001 /
bx0 +
b1000 -
1"
#346000
0"
#347000
b10110101011001 !
b10110101011001 0
1"
#348000
0"
#349000
1"
#350000
0"
#351000
1"
#352000
0"
#353000
1"
#354000
0"
#355000
1"
#356000
0"
#357000
1"
#358000
0"
#359000
1"
#360000
0"
#361000
1"
#362000
0"
#363000
1"
#364000
0"
#365000
1"
#366000
0"
#367000
1"
#368000
0"
#369000
1"
#370000
0"
#371000
1"
#372000
0"
#373000
1"
#374000
0"
#375000
1"
#376000
0"
#377000
1"
#378000
0"
#379000
1"
#380000
0"
1%
#381000
b0 !
b0 0
0,
b0 .
b0 -
b0 1
b0 /
b0 +
1"
#382000
0"
#383000
1"
#384000
0"
#385000
b1101001111111111 (
b11111111111111111101001010100111 !
b11111111111111111101001010100111 0
b11111111111111111101001010100111 /
b1 -
1,
b111 +
b1100110011011111 )
b10110000000001 *
1"
b1100110011011111 $
b1100110011011111 '
b10110000000001 #
b10110000000001 &
0%
#386000
0"
#387000
b11 +
b10 -
1"
#388000
0"
#389000
b1010101001011000111 !
b1010101001011000111 0
b1011000000000100000 1
b100 .
b101100000000010 /
b110 +
b11 -
1"
#390000
0"
#391000
b11111111111110100101001010000111 !
b11111111111110100101001010000111 0
b11111111111101001111111111000000 1
b110 .
12
b11111111111111111101001111111111 /
b1 +
b100 -
1"
#392000
0"
#393000
b1001100101001110000111 !
b1001100101001110000111 0
b1011000000000100000000 1
b1000 .
02
b10110000000001 /
b110 +
b101 -
1"
#394000
0"
#395000
b11111111011101100100111110000111 !
b11111111011101100100111110000111 0
b11111111010011111111110000000000 1
b1010 .
12
b11111111111111111101001111111111 /
b1 +
b110 -
1"
#396000
0"
#397000
b10001101100101111110000111 !
b10001101100101111110000111 0
b10110000000001000000000000 1
b1100 .
02
b10110000000001 /
b10 +
b111 -
1"
#398000
0"
#399000
b1101001101101001111110000111 !
b1101001101101001111110000111 0
b1011000000000100000000000000 1
b1110 .
bx1 +
b1000 -
1"
#400000
0"
#401000
b10110000000001 !
b10110000000001 0
1"
#402000
0"
#403000
1"
#404000
0"
#405000
1"
#406000
0"
#407000
1"
#408000
0"
#409000
1"
#410000
0"
#411000
1"
#412000
0"
#413000
1"
#414000
0"
#415000
1"
#416000
0"
#417000
1"
#418000
0"
#419000
1"
#420000
0"
#421000
1"
#422000
0"
#423000
1"
#424000
0"
#425000
1"
#426000
0"
#427000
1"
#428000
0"
#429000
1"
#430000
0"
#431000
1"
#432000
0"
#433000
1"
#434000
0"
#435000
b0 !
b0 0
0,
b0 .
b0 -
b0 1
b0 /
b0 +
1"
1%
