RV32_APX/Definitions.v
/*
      Avaiable instructions in the RV32-APX CPU:

      ADD rd,rs1,rs2 (Approximate ADD)
      AND rd,rs1,rs2
      OR  rd,rs1,rs2
      XOR AND rd,rs1,rs2

*/

`define RTYPE 51
`define ITYPE 3
`define STYPE 35
`define BTYPE 32
`define UTYPE 42
`define JTYPE 99

`define ALU_OP_AND 0
`define ALU_OP_OR 1
`define ALU_OP_ADD 2
`define ALU_OP_SLL 3
`define ALU_OP_SLT 4
`define ALU_OP_SLTU 5
`define ALU_OP_ApproxAdd 6
`define ALU_OP_XOR 7
`define ALU_OP_SRL 8
`define ALU_OP_SRA 9

`define AND 0
`define OR 1
`define ADD 2
`define SLL 3
`define SLT 4
`define SLTU 5
`define SUB 6
`define XOR 7
`define SRL 8
`define SRA 9

RV32_APX/Program_Counter.v
module PC_Assign
(
      input reset, 
      input [31:0] pc,
      output reg [31:0] read_address
);
  always @(reset, pc) begin
    if(reset == 1) begin
      read_address <=0;
    end
    if (reset == 0) begin
      read_address <= pc;
    end
  end
endmodule

module PC_MUX
(
  input wire reset,
  output reg [31:0] pc,
  input wire [31:0] pc_address,
  input wire [31:0] jmp_address,  
  input wire pc_select
);

  always @(reset, pc_select, jmp_address, pc_address) begin
    if (reset == 1) begin
      pc <= 0;
    end 
    else begin
      if (pc_select) 
      begin
        pc <= jmp_address;
      end 
      else begin
        pc <= pc_address;
      end
    end
  end
endmodule

module PC_Adder
(
      input wire reset, 
      input wire step, 
      input wire [31:0] pc, 
      output reg [31:0] pc_address
);
  always @(posedge step, posedge reset) begin
    if (reset == 1) begin
      pc_address <= 0;
    end
    else begin
    if (reset == 0) begin
      pc_address <= pc + 1;
    end
    end
  end
endmodule

module JMP_Adder
(
    input wire reset,
    input wire [31:0] read_address,
    input wire [31:0] immediate_gen,
    output reg [31:0] jmp_address
);
always @(read_address, reset, immediate_gen) begin
  if (reset == 1) begin
    jmp_address <= 0;
  end   
  if (reset == 0) begin
      jmp_address = (read_address + immediate_gen);
  end
end
endmodule

module taken
(
      input wire [31:0] result,
      input wire branch,
      output reg pc_select
);
always @(branch, result) begin
    if (!result && branch)
        pc_select <= 1;
    else
        pc_select <= 0;
end
endmodule

RV32_APX/Immediate_Generator.v
module Immediate_Generator
(
  input wire reset,
  input wire [31:0] instruction,
  output reg [31:0] immediate_gen
);

  reg [19:0] high_bit;

  always @(reset, instruction) 
  begin
    if(reset == 1) 
    begin
      immediate_gen <= 0;
    end

    if (reset == 0) 
    begin
      if (instruction[6:0] == `ITYPE) begin
        immediate_gen[12-1:0] <= instruction[31:20];
      end 
      else if (instruction[6:0] == `STYPE) begin
        immediate_gen[11:5] <= instruction[31:25];
        immediate_gen[4:0] <= instruction[11:7];
      end 
      else if (instruction[6:0] == `JTYPE) begin
        immediate_gen[12] <= instruction[31];
        immediate_gen[10:5] <= instruction[30:25];
        immediate_gen[11] <= instruction[7];
        immediate_gen[5-1:1] <= instruction[11:8];
        immediate_gen[0] <= 0;
      end
      if (instruction[31] == 0) begin
        high_bit <= 0;
        immediate_gen[31:12] <= high_bit;
      end 
      else begin
        high_bit = 20'hfffff;
        immediate_gen[31:12] <= high_bit;
      end
    end
  end

endmodule

RV32_APX/Register_File.v
module Register_File
(
  input wire reset,
  input wire clk,
  input wire [4:0] read_a_select,
  input wire [4:0] read_b_select,
  input wire [4:0] write_a_select,
  input wire [31:0] write_a,
  input wire write_flag,
  output reg [31:0] read_a,
  output reg [31:0] read_b
);

  reg [31:0] registers [0:31];

  integer i,file;
  always @(reset, read_b_select, read_a_select, registers[i]) 
  begin

    if(reset == 1) begin
      read_a <= 0;
      read_b <= 0;
      for(i = 0; i < 32; i = i + 1) 
      begin
        registers[i]<=1;
      end     
      end

    if (reset == 0) begin
      if (read_a_select != 0) begin
        read_a <= registers[read_a_select];
      end
      if (read_b_select != 0) begin
        read_b <= registers[read_b_select];
      end
    end

  end
  
  always @(posedge clk) begin
    if (reset == 0) begin
      if (write_flag && (write_a_select > 0)) 
      begin
         registers[write_a_select] <= write_a;
         file = $fopen("C:/Users/ASUS/OneDrive/Desktop/Project Proposal/RV32_APX/output.txt", "a");
         $fwrite(file, "%d\n", write_a);
      end
    end
  end
endmodule

module Write_MUX 
(
  input wire reset,
  output reg [31:0] write_a,
  input wire mem_to_regs,
  input wire [31:0] result,
  input wire [31:0] read_data
);
always @(reset, mem_to_regs, read_data, result) begin
  if (reset == 1) 
  begin
      write_a <= 0;
  end
  if (reset == 0) 
  begin
    if (mem_to_regs)
      write_a <= read_data;
    else
      write_a <= result;
  end
end
endmodule

RV32_APX/ALU.v
module ALU 
(
    input wire reset, 
    input wire [4:0]  alu_decode, 
    input wire [31:0] read_a, 
    input wire [31:0] read_x, 
    output reg [31:0] result
);
    always @(reset, alu_decode, read_a, read_x) begin
        if (reset==1) begin
          result <= 0;
        end
        if (reset == 0) begin
            case (alu_decode)
                `ALU_OP_AND: result <= read_a & read_x;
                `ALU_OP_OR:  result <= read_a | read_x;
                `ALU_OP_ADD: result <= read_a + read_x;
                `ALU_OP_ApproxAdd: begin //GeAr(32,2,6)
                    result[7:0]   <= (read_a[7:0] ^ read_x[7:0]) + ((read_a[7:0] & read_x[7:0]) << 1);
                    result[9:8]   <= (read_a[9:8] ^ read_x[9:8]) + ((read_a[9:8] & read_x[9:8]) << 1);
                    result[11:10] <= (read_a[11:10] ^ read_x[11:10]) + ((read_a[11:10] & read_x[11:10]) << 1);
                    result[13:12] <= (read_a[13:12] ^ read_x[13:12]) + ((read_a[13:12] & read_x[13:12]) << 1);
                    result[15:14] <= (read_a[15:14] ^ read_x[15:14]) + ((read_a[15:14] & read_x[15:14]) << 1);
                    result[17:16] <= (read_a[17:16] ^ read_x[17:16]) + ((read_a[17:16] & read_x[17:16]) << 1);
                    result[19:18] <= (read_a[19:18] ^ read_x[19:18]) + ((read_a[19:18] & read_x[19:18]) << 1);
                    result[21:20] <= (read_a[21:20] ^ read_x[21:20]) + ((read_a[21:20] & read_x[21:20]) << 1);
                    result[23:22] <= (read_a[23:22] ^ read_x[23:22]) + ((read_a[23:22] & read_x[23:22]) << 1);
                    result[25:24] <= (read_a[25:24] ^ read_x[25:24]) + ((read_a[25:24] & read_x[25:24]) << 1);
                    result[27:26] <= (read_a[27:26] ^ read_x[27:26]) + ((read_a[27:26] & read_x[27:26]) << 1);
                    result[29:28] <= (read_a[29:28] ^ read_x[29:28]) + ((read_a[29:28] & read_x[29:28]) << 1);
                    result[31:30] <= (read_a[31:30] ^ read_x[31:30]) + ((read_a[31:30] & read_x[31:30]) << 1);
                    end
                `ALU_OP_XOR:  result <= read_a ^ read_x;
                `ALU_OP_SLL:  result <= read_a << read_x;
                `ALU_OP_SRL:  result <= read_a >> read_x;
                `ALU_OP_SLT:  result <= (read_a < read_x) ? 1 : 0;
                `ALU_OP_SLTU: result <= (read_a < read_x) ? 1 : 0;
                `ALU_OP_SRA:  result <= (read_a[31] == 1) ? (read_a >> read_x) | ((1 << (32 - read_x)) - 1) : (read_a >> read_x);
                default:      result <= 0;
            endcase
        end
    end  
endmodule

module ALU_Control
(
  input wire reset,
  input wire [31:0] instruction,
  input wire [3:0] alu_operation,
  output reg [3:0] alu_decode
);
  always @(instruction, reset, alu_operation) 
  begin
    if(reset == 1) begin
      alu_decode<=0;
    end
    if (reset == 0) begin
      if (alu_operation == 2) 
      begin
        if (instruction[31:25] == 0) 
        begin
          if (instruction[14:12] == 0) begin
            alu_decode <= `ADD;
          end else if (instruction[14:12] == 1) begin
            alu_decode <= `SLL;
          end else if (instruction[14:12] == 2) begin
            alu_decode <= `SLT;
          end else if (instruction[14:12] == 3) begin
            alu_decode <= `SLTU;
          end else if (instruction[14:12] == 4) begin
            alu_decode<= `XOR;
          end else if (instruction[14:12] == 5) begin
            alu_decode <= `SRL;
          end else if (instruction[14:12] == 6) begin
            alu_decode <= `OR;
          end else if (instruction[14:12] == 7) begin
            alu_decode <= `AND;
          end
        end 
        else if (instruction[31:25] == 32) begin
          if (instruction[14:12] == 0) begin
            alu_decode <= `SUB;
          end else if (instruction[14:12] == 5) begin
            alu_decode <= `SRA;
          end
        end
      end 
      else if (alu_operation == 0) begin
        alu_decode <= `ADD;
      end 
      else if (alu_operation == 7) begin
        if (instruction[14:12] == 0) 
        begin
          alu_decode <= `XOR;
        end
      end
    end
  end
endmodule

module ALU_MUX 
(
     input wire reset,
     input wire alu_src,
     input wire [31:0] immediate_gen,
     input wire [31:0] read_b,
     output reg [31:0] read_x    
);
      always @(reset, immediate_gen, alu_src, read_b) 
      begin
        if (reset == 1) begin
          read_x <= 0;
        end
        if (reset == 0) begin
            if (alu_src) begin
                read_x <= immediate_gen;
            end 
            else begin
                read_x <= read_b;
            end
        end
      end
endmodule

RV32_APX/Memories.v
module Instruction_Memory
(
  input wire reset,
  input wire [31:0] read_address,
  output reg [31:0] instruction,
  output reg [4:0] read_a_select,
  output reg [4:0] read_b_select,
  output reg [4:0] write_a_select,
  output reg [6:0] opcode
);

  reg [31:0] inst_ram [0:1048576-1];
  
  initial begin
    $readmemb("C:/Users/ASUS/OneDrive/Desktop/Project Proposal/RV32_APX/imem.txt", inst_ram);
  end
  
  always @(reset, read_address, inst_ram[read_address]) 
  begin

    if (reset == 1) 
    begin
      instruction <= 0;
      write_a_select <= 0;
      read_a_select <= 0;
      read_b_select <= 0;
      opcode <= 0;
    end

    if (reset == 0) 
    begin
      instruction <= inst_ram[read_address];
      case (inst_ram[read_address][6:0])
        `RTYPE: begin
          read_a_select <= inst_ram[read_address][19:15];
          read_b_select <= inst_ram[read_address][24:20];
          opcode <= inst_ram[read_address][6:0];
          write_a_select <= inst_ram[read_address][11:7];
        end
        `ITYPE: begin
          read_a_select <= inst_ram[read_address][19:15];
          opcode <= inst_ram[read_address][6:0];
          write_a_select <= inst_ram[read_address][11:7];
        end
        `STYPE: begin
          read_a_select <= inst_ram[read_address][19:15];
          read_b_select <= inst_ram[read_address][24:20];
          opcode <= inst_ram[read_address][6:0];
          write_a_select <= inst_ram[read_address][24:20];
        end
        `JTYPE: begin
          read_a_select <= inst_ram[read_address][19:15];
          read_b_select <= inst_ram[read_address][24:20];
          opcode <= inst_ram[read_address][6:0];
        end
      endcase
    end
  end
  
endmodule

module Data_Memory
(
    input wire reset,
    input wire clk,
    input wire [31:0] result,
    input wire mem_write,
    input wire mem_read,
    input wire [31:0] read_b,
    output reg [31:0] read_data
);
    reg [31:0] data_ram[0:2048-1]; 
    
    initial begin
        $readmemb("C:/Users/ASUS/OneDrive/Desktop/Project Proposal/RV32_APX/dmem.txt", data_ram);
    end
    
    always @(reset) 
    begin
      if (reset == 1) 
      begin
        read_data <= 0;
      end
    end

    always @(posedge clk) 
    begin
        if (reset == 1) 
        begin
          read_data <=0 ;
        end
        if (reset == 0) 
        begin
            if (mem_write) begin
                data_ram[result] <= read_b;
            end
            else if (mem_read) begin
                read_data <= data_ram[result];
            end
        end
    end
endmodule

RV32_APX/Control_Unit.v
module Control_Unit 
(
  input wire reset,
  input wire [6:0] opcode,
  output reg branch,
  output reg mem_read,
  output reg mem_to_regs,
  output reg [3:0] alu_operation,
  output reg mem_write,
  output reg alu_src,
  output reg reg_write
);

always @(reset, opcode) begin
  if (reset == 1) begin
              alu_src <= 0;
              mem_to_regs <= 0;
              reg_write <= 0;
              mem_read <= 0;
              mem_write <= 0;
              branch <= 0;
              alu_operation <= 0;
  end
  if (reset == 0) begin
      case (opcode)
          'h33: begin
              alu_src <= 0;
              mem_to_regs <= 0;
              reg_write <= 1;
              mem_read <= 0;
              mem_write <= 0;
              branch <= 0;
              alu_operation <= 2;
          end
          'h3: begin
              alu_src <= 1;
              mem_to_regs <= 1;
              reg_write <= 1;
              mem_read <= 1;
              mem_write <= 0;
              branch <= 0;
              alu_operation <= 0;
          end
          'h23: begin
              alu_src <= 1;
              mem_to_regs <= 0;
              reg_write <= 0;
              mem_read <= 0;
              mem_write <= 1;
              branch <= 0;
              alu_operation <= 0;
          end
          'h63: begin
              alu_src <= 0;
              mem_to_regs <= 0;
              reg_write <= 0;
              mem_read <= 0;
              mem_write <= 0;
              branch <= 1;
              alu_operation <= 7;
          end
      endcase
  end
end
endmodule

RV32_APX/RV32_APX_CORE.v
`include "Definitions.v"
`include "Control_Unit.v"
`include "Register_File.v"
`include "Program_Counter.v"
`include "Immediate_Generator.v"
`include "ALU.v"
`include "Memories.v"

`timescale 1ns/100ps

module RV32_APX_CORE
(
      input wire clk,
      input wire reset
);
  wire pc_select;
  wire branch, mem_read, mem_to_regs, mem_write, alu_src, reg_write;
  wire [4:0] read_a_select, read_b_select, write_a_select;
  wire [31:0] write_a, read_a, read_b, read_x;
  wire [3:0] alu_operation;
  wire [6:0] opcode;
  wire [31:0] pc, result, read_data, shl;
  reg  [31:0] aux;
  wire [31:0] immediate_gen;
  wire [3:0] alu_decode;
  reg step;
  wire [31:0] read_address, instruction, pc_address, jmp_address;

    initial begin
      step <= 0;
    end
    
  Control_Unit control(reset, opcode, branch, mem_read, mem_to_regs, alu_operation, mem_write, alu_src, reg_write);
  
  Data_Memory dmem(reset, clk, result, mem_write, mem_read, read_b, read_data);
  Instruction_Memory imem(reset, read_address, instruction, read_a_select, read_b_select, write_a_select, opcode);
  
  ALU ALU_APX(reset, alu_decode, read_a, read_x, result);
  ALU_MUX ALU_APX_MUX(reset, alu_src, immediate_gen, read_a, read_x);
  ALU_Control ALU_APX_Control(reset, instruction, alu_operation, alu_decode);

  Register_File Reg_File(reset, clk, read_a_select, read_b_select, write_a_select, write_a, reg_write, read_a, read_b);
  
  PC_Adder pc_add(reset, step, pc, pc_address);
  JMP_Adder jmp_add(reset, read_address, immediate_gen, jmp_address);
  PC_MUX ProgramCounter_mux(reset, pc, pc_address, jmp_address, pc_select);
  PC_Assign next_pc(reset, pc, read_address);

  
  Write_MUX write(reset, write_a, mem_to_regs, result, read_data);
  Immediate_Generator imm_gen(reset, instruction, immediate_gen);
  taken tkn(result, branch, pc_select);

  always @(posedge clk)
  begin
  if (reset == 0)
    begin
      step <= ~step;
    end
  end
endmodule

module clock_generator(output reg clk);
  always #5 clk <= ~clk;
endmodule

RV32_APX/CPU_testbench.v
`include "RV32_APX_CORE.v"
`timescale 1ns/100ps

module CPU_testbench();

  reg clk;
  reg reset;
  
  always #10 clk <= ~clk;
  RV32_APX_CORE CPU(.clk(clk), .reset(reset));
  
  initial begin
      $dumpfile("RV32_APX.vcd");
      $dumpvars(0, CPU_testbench);
      reset <= 1;
      clk <= 0;
      #1 reset = ~reset;
  end
  initial
   #60000 $finish;
  
endmodule

RV32_APX/RV32_APX.vcd
$date
	Tue May 16 19:38:32 2023
$end
$version
	Icarus Verilog
$end
$timescale
	100ps
$end
$scope module CPU_testbench $end
$var reg 1 ! clk $end
$var reg 1 " reset $end
$scope module CPU $end
$var wire 1 ! clk $end
$var wire 1 " reset $end
$var wire 5 # write_a_select [4:0] $end
$var wire 32 $ write_a [31:0] $end
$var wire 32 % result [31:0] $end
$var wire 1 & reg_write $end
$var wire 32 ' read_x [31:0] $end
$var wire 32 ( read_data [31:0] $end
$var wire 5 ) read_b_select [4:0] $end
$var wire 32 * read_b [31:0] $end
$var wire 32 + read_address [31:0] $end
$var wire 5 , read_a_select [4:0] $end
$var wire 32 - read_a [31:0] $end
$var wire 1 . pc_select $end
$var wire 32 / pc_address [31:0] $end
$var wire 32 0 pc [31:0] $end
$var wire 7 1 opcode [6:0] $end
$var wire 1 2 mem_write $end
$var wire 1 3 mem_to_regs $end
$var wire 1 4 mem_read $end
$var wire 32 5 jmp_address [31:0] $end
$var wire 32 6 instruction [31:0] $end
$var wire 32 7 immediate_gen [31:0] $end
$var wire 1 8 branch $end
$var wire 1 9 alu_src $end
$var wire 4 : alu_operation [3:0] $end
$var wire 4 ; alu_decode [3:0] $end
$var reg 1 < step $end
$scope module ALU_APX $end
$var wire 5 = alu_decode [4:0] $end
$var wire 1 " reset $end
$var wire 32 > read_x [31:0] $end
$var wire 32 ? read_a [31:0] $end
$var reg 32 @ result [31:0] $end
$upscope $end
$scope module ALU_APX_Control $end
$var wire 1 " reset $end
$var wire 32 A instruction [31:0] $end
$var wire 4 B alu_operation [3:0] $end
$var reg 4 C alu_decode [3:0] $end
$upscope $end
$scope module ALU_APX_MUX $end
$var wire 1 " reset $end
$var wire 32 D read_b [31:0] $end
$var wire 32 E immediate_gen [31:0] $end
$var wire 1 9 alu_src $end
$var reg 32 F read_x [31:0] $end
$upscope $end
$scope module ProgramCounter_mux $end
$var wire 1 " reset $end
$var wire 1 . pc_select $end
$var wire 32 G pc_address [31:0] $end
$var wire 32 H jmp_address [31:0] $end
$var reg 32 I pc [31:0] $end
$upscope $end
$scope module Reg_File $end
$var wire 1 ! clk $end
$var wire 1 " reset $end
$var wire 1 & write_flag $end
$var wire 5 J write_a_select [4:0] $end
$var wire 32 K write_a [31:0] $end
$var wire 5 L read_b_select [4:0] $end
$var wire 5 M read_a_select [4:0] $end
$var reg 32 N read_a [31:0] $end
$var reg 32 O read_b [31:0] $end
$var integer 32 P file [31:0] $end
$var integer 32 Q i [31:0] $end
$upscope $end
$scope module control $end
$var wire 1 " reset $end
$var wire 7 R opcode [6:0] $end
$var reg 4 S alu_operation [3:0] $end
$var reg 1 9 alu_src $end
$var reg 1 8 branch $end
$var reg 1 4 mem_read $end
$var reg 1 3 mem_to_regs $end
$var reg 1 2 mem_write $end
$var reg 1 & reg_write $end
$upscope $end
$scope module dmem $end
$var wire 1 ! clk $end
$var wire 1 4 mem_read $end
$var wire 1 2 mem_write $end
$var wire 32 T read_b [31:0] $end
$var wire 1 " reset $end
$var wire 32 U result [31:0] $end
$var reg 32 V read_data [31:0] $end
$upscope $end
$scope module imem $end
$var wire 1 " reset $end
$var wire 32 W read_address [31:0] $end
$var reg 32 X instruction [31:0] $end
$var reg 7 Y opcode [6:0] $end
$var reg 5 Z read_a_select [4:0] $end
$var reg 5 [ read_b_select [4:0] $end
$var reg 5 \ write_a_select [4:0] $end
$upscope $end
$scope module imm_gen $end
$var wire 32 ] instruction [31:0] $end
$var wire 1 " reset $end
$var reg 20 ^ high_bit [19:0] $end
$var reg 32 _ immediate_gen [31:0] $end
$upscope $end
$scope module jmp_add $end
$var wire 32 ` immediate_gen [31:0] $end
$var wire 1 " reset $end
$var wire 32 a read_address [31:0] $end
$var reg 32 b jmp_address [31:0] $end
$upscope $end
$scope module next_pc $end
$var wire 32 c pc [31:0] $end
$var wire 1 " reset $end
$var reg 32 d read_address [31:0] $end
$upscope $end
$scope module pc_add $end
$var wire 32 e pc [31:0] $end
$var wire 1 " reset $end
$var wire 1 < step $end
$var reg 32 f pc_address [31:0] $end
$upscope $end
$scope module tkn $end
$var wire 1 8 branch $end
$var wire 32 g result [31:0] $end
$var reg 1 . pc_select $end
$upscope $end
$scope module write $end
$var wire 1 3 mem_to_regs $end
$var wire 32 h read_data [31:0] $end
$var wire 1 " reset $end
$var wire 32 i result [31:0] $end
$var reg 32 j write_a [31:0] $end
$upscope $end
$upscope $end
$upscope $end
$enddefinitions $end
$comment Show the parameter values. $end
$dumpall
$end
#0
$dumpvars
b0 j
b0 i
b0 h
b0 g
b0 f
b0 e
b0 d
b0 c
b0 b
b0 a
b0 `
b0 _
bx ^
b0 ]
b0 \
b0 [
b0 Z
b0 Y
b0 X
b0 W
b0 V
b0 U
b0 T
b0 S
b0 R
b100000 Q
bx P
b0 O
b0 N
b0 M
b0 L
b0 K
b0 J
b0 I
b0 H
b0 G
b0 F
b0 E
b0 D
b0 C
b0 B
b0 A
b0 @
b0 ?
b0 >
b0 =
0<
b0 ;
b0 :
09
08
b0 7
b0 6
b0 5
04
03
02
b0 1
b0 0
b0 /
0.
b0 -
b0 ,
b0 +
b0 *
b0 )
b0 (
b0 '
0&
b0 %
b0 $
b0 #
1"
0!
$end
#10
b1 %
b1 @
b1 U
b1 g
b1 i
14
1&
13
19
b1 -
b1 ?
b1 D
b1 N
b0 5
b0 H
b0 b
b10 =
b10 ;
b10 C
b101 #
b101 J
b101 \
b11 1
b11 R
b11 Y
b101 ,
b101 M
b101 Z
b101010001010000011 6
b101010001010000011 A
b101010001010000011 X
b101010001010000011 ]
b0 7
b0 E
b0 _
b0 `
b0 ^
0"
#100
b11000101000001000010011 6
b11000101000001000010011 A
b11000101000001000010011 X
b11000101000001000010011 ]
b1 5
b1 H
b1 b
b1 +
b1 W
b1 a
b1 d
b1 0
b1 I
b1 c
b1 e
b11100000011111001101000001001 $
b11100000011111001101000001001 K
b11100000011111001101000001001 j
b1 /
b1 G
b1 f
b11100000011111001101000001001 (
b11100000011111001101000001001 V
b11100000011111001101000001001 h
1<
b10000000000000000000000000000011 P
1!
#200
0!
#300
0<
b10000000000000000000000000000100 P
1!
#400
0!
#500
b11100101000001110010011 6
b11100101000001110010011 A
b11100101000001110010011 X
b11100101000001110010011 ]
b10 5
b10 H
b10 b
b10 +
b10 W
b10 a
b10 d
b10 0
b10 I
b10 c
b10 e
b10 /
b10 G
b10 f
1<
b10000000000000000000000000000101 P
1!
#600
0!
#700
0<
b10000000000000000000000000000110 P
1!
#800
0!
#900
b10 %
b10 @
b10 U
b10 g
b10 i
b10 $
b10 K
b10 j
b1 '
b1 >
b1 F
b10 :
b10 B
b10 S
04
03
09
b1 *
b1 O
b1 T
b1000 #
b1000 J
b1000 \
b110011 1
b110011 R
b110011 Y
b111 )
b111 L
b111 [
b100 ,
b100 M
b100 Z
b11100100000010000110011 6
b11100100000010000110011 A
b11100100000010000110011 X
b11100100000010000110011 ]
b11 5
b11 H
b11 b
b11 +
b11 W
b11 a
b11 d
b11 0
b11 I
b11 c
b11 e
b11 /
b11 G
b11 f
1<
b10000000000000000000000000000111 P
1!
#1000
0!
#1100
0<
b10000000000000000000000000001000 P
1!
#1200
0!
#1300
b11111111111111111111000000000000 7
b11111111111111111111000000000000 E
b11111111111111111111000000000000 _
b11111111111111111111000000000000 `
b11111111111111111111 ^
b11111111000111111111001011101111 6
b11111111000111111111001011101111 A
b11111111000111111111001011101111 X
b11111111000111111111001011101111 ]
b11111111111111111111000000000100 5
b11111111111111111111000000000100 H
b11111111111111111111000000000100 b
b100 +
b100 W
b100 a
b100 d
b100 0
b100 I
b100 c
b100 e
b100 /
b100 G
b100 f
1<
b10000000000000000000000000001001 P
1!
#1400
0!
#1500
0<
b10000000000000000000000000001010 P
1!
#1600
0!
#1700
bx 6
bx A
bx X
bx ]
b11111111111111111111000000000101 5
b11111111111111111111000000000101 H
b11111111111111111111000000000101 b
b101 +
b101 W
b101 a
b101 d
b101 0
b101 I
b101 c
b101 e
b101 /
b101 G
b101 f
1<
b10000000000000000000000000001011 P
1!
#1800
0!
#1900
0<
b10000000000000000000000000001100 P
1!
#2000
0!
#2100
b11111111111111111111000000000110 5
b11111111111111111111000000000110 H
b11111111111111111111000000000110 b
b110 +
b110 W
b110 a
b110 d
b110 0
b110 I
b110 c
b110 e
b110 /
b110 G
b110 f
1<
b10000000000000000000000000001101 P
1!
#2200
0!
#2300
0<
b10000000000000000000000000001110 P
1!
#2400
0!
#2500
b11111111111111111111000000000111 5
b11111111111111111111000000000111 H
b11111111111111111111000000000111 b
b111 +
b111 W
b111 a
b111 d
b111 0
b111 I
b111 c
b111 e
b111 /
b111 G
b111 f
1<
b10000000000000000000000000001111 P
1!
#2600
0!
#2700
0<
b10000000000000000000000000010000 P
1!
#2800
0!
#2900
b11111111111111111111000000001000 5
b11111111111111111111000000001000 H
b11111111111111111111000000001000 b
b1000 +
b1000 W
b1000 a
b1000 d
b1000 0
b1000 I
b1000 c
b1000 e
b1000 /
b1000 G
b1000 f
1<
b10000000000000000000000000010001 P
1!
#3000
0!
#3100
0<
b10000000000000000000000000010010 P
1!
#3200
0!
#3300
b11111111111111111111000000001001 5
b11111111111111111111000000001001 H
b11111111111111111111000000001001 b
b1001 +
b1001 W
b1001 a
b1001 d
b1001 0
b1001 I
b1001 c
b1001 e
b1001 /
b1001 G
b1001 f
1<
b10000000000000000000000000010011 P
1!
#3400
0!
#3500
0<
b10000000000000000000000000010100 P
1!
#3600
0!
#3700
b11111111111111111111000000001010 5
b11111111111111111111000000001010 H
b11111111111111111111000000001010 b
b1010 +
b1010 W
b1010 a
b1010 d
b1010 0
b1010 I
b1010 c
b1010 e
b1010 /
b1010 G
b1010 f
1<
b10000000000000000000000000010101 P
1!
#3800
0!
#3900
0<
b10000000000000000000000000010110 P
1!
#4000
0!
#4100
b11111111111111111111000000001011 5
b11111111111111111111000000001011 H
b11111111111111111111000000001011 b
b1011 +
b1011 W
b1011 a
b1011 d
b1011 0
b1011 I
b1011 c
b1011 e
b1011 /
b1011 G
b1011 f
1<
b10000000000000000000000000010111 P
1!
#4200
0!
#4300
0<
b10000000000000000000000000011000 P
1!
#4400
0!
#4500
b11111111111111111111000000001100 5
b11111111111111111111000000001100 H
b11111111111111111111000000001100 b
b1100 +
b1100 W
b1100 a
b1100 d
b1100 0
b1100 I
b1100 c
b1100 e
b1100 /
b1100 G
b1100 f
1<
b10000000000000000000000000011001 P
1!
#4600
0!
#4700
0<
b10000000000000000000000000011010 P
1!
#4800
0!
#4900
b11111111111111111111000000001101 5
b11111111111111111111000000001101 H
b11111111111111111111000000001101 b
b1101 +
b1101 W
b1101 a
b1101 d
b1101 0
b1101 I
b1101 c
b1101 e
b1101 /
b1101 G
b1101 f
1<
b10000000000000000000000000011011 P
1!
#5000
0!
#5100
0<
b10000000000000000000000000011100 P
1!
#5200
0!
#5300
b11111111111111111111000000001110 5
b11111111111111111111000000001110 H
b11111111111111111111000000001110 b
b1110 +
b1110 W
b1110 a
b1110 d
b1110 0
b1110 I
b1110 c
b1110 e
b1110 /
b1110 G
b1110 f
1<
b10000000000000000000000000011101 P
1!
#5400
0!
#5500
0<
b10000000000000000000000000011110 P
1!
#5600
0!
#5700
b11111111111111111111000000001111 5
b11111111111111111111000000001111 H
b11111111111111111111000000001111 b
b1111 +
b1111 W
b1111 a
b1111 d
b1111 0
b1111 I
b1111 c
b1111 e
b1111 /
b1111 G
b1111 f
1<
b10000000000000000000000000011111 P
1!
#5800
0!
#5900
0<
b10000000000000000000000000100000 P
1!
#6000
0!
#6100
b11111111111111111111000000010000 5
b11111111111111111111000000010000 H
b11111111111111111111000000010000 b
b10000 +
b10000 W
b10000 a
b10000 d
b10000 0
b10000 I
b10000 c
b10000 e
b10000 /
b10000 G
b10000 f
1<
b10000000000000000000000000100001 P
1!
#6200
0!
#6300
0<
b10000000000000000000000000100010 P
1!
#6400
0!
#6500
b11111111111111111111000000010001 5
b11111111111111111111000000010001 H
b11111111111111111111000000010001 b
b10001 +
b10001 W
b10001 a
b10001 d
b10001 0
b10001 I
b10001 c
b10001 e
b10001 /
b10001 G
b10001 f
1<
b10000000000000000000000000100011 P
1!
#6600
0!
#6700
0<
b10000000000000000000000000100100 P
1!
#6800
0!
#6900
b11111111111111111111000000010010 5
b11111111111111111111000000010010 H
b11111111111111111111000000010010 b
b10010 +
b10010 W
b10010 a
b10010 d
b10010 0
b10010 I
b10010 c
b10010 e
b10010 /
b10010 G
b10010 f
1<
b10000000000000000000000000100101 P
1!
#7000
0!
#7100
0<
b10000000000000000000000000100110 P
1!
#7200
0!
#7300
b11111111111111111111000000010011 5
b11111111111111111111000000010011 H
b11111111111111111111000000010011 b
b10011 +
b10011 W
b10011 a
b10011 d
b10011 0
b10011 I
b10011 c
b10011 e
b10011 /
b10011 G
b10011 f
1<
b10000000000000000000000000100111 P
1!
#7400
0!
#7500
0<
b10000000000000000000000000101000 P
1!
#7600
0!
#7700
b11111111111111111111000000010100 5
b11111111111111111111000000010100 H
b11111111111111111111000000010100 b
b10100 +
b10100 W
b10100 a
b10100 d
b10100 0
b10100 I
b10100 c
b10100 e
b10100 /
b10100 G
b10100 f
1<
b10000000000000000000000000101001 P
1!
#7800
0!
#7900
0<
b10000000000000000000000000101010 P
1!
#8000
0!
#8100
b11111111111111111111000000010101 5
b11111111111111111111000000010101 H
b11111111111111111111000000010101 b
b10101 +
b10101 W
b10101 a
b10101 d
b10101 0
b10101 I
b10101 c
b10101 e
b10101 /
b10101 G
b10101 f
1<
b10000000000000000000000000101011 P
1!
#8200
0!
#8300
0<
b10000000000000000000000000101100 P
1!
#8400
0!
#8500
b11111111111111111111000000010110 5
b11111111111111111111000000010110 H
b11111111111111111111000000010110 b
b10110 +
b10110 W
b10110 a
b10110 d
b10110 0
b10110 I
b10110 c
b10110 e
b10110 /
b10110 G
b10110 f
1<
b10000000000000000000000000101101 P
1!
#8600
0!
#8700
0<
b10000000000000000000000000101110 P
1!
#8800
0!
#8900
b11111111111111111111000000010111 5
b11111111111111111111000000010111 H
b11111111111111111111000000010111 b
b10111 +
b10111 W
b10111 a
b10111 d
b10111 0
b10111 I
b10111 c
b10111 e
b10111 /
b10111 G
b10111 f
1<
b10000000000000000000000000101111 P
1!
#9000
0!
#9100
0<
b10000000000000000000000000110000 P
1!
#9200
0!
#9300
b11111111111111111111000000011000 5
b11111111111111111111000000011000 H
b11111111111111111111000000011000 b
b11000 +
b11000 W
b11000 a
b11000 d
b11000 0
b11000 I
b11000 c
b11000 e
b11000 /
b11000 G
b11000 f
1<
b10000000000000000000000000110001 P
1!
#9400
0!
#9500
0<
b10000000000000000000000000110010 P
1!
#9600
0!
#9700
b11111111111111111111000000011001 5
b11111111111111111111000000011001 H
b11111111111111111111000000011001 b
b11001 +
b11001 W
b11001 a
b11001 d
b11001 0
b11001 I
b11001 c
b11001 e
b11001 /
b11001 G
b11001 f
1<
b10000000000000000000000000110011 P
1!
#9800
0!
#9900
0<
b10000000000000000000000000110100 P
1!
#10000
0!
